hwindow-1.1.3.dist-info/licenses/LICENSE.txt
hwindow1/__init__.py
hwindow1/data/Core/Hwindow.pyd
hwindow1/data/Core/Hwindow.pyi
hwindow1/data/Core/Qt6Core.dll
hwindow1/data/Core/Qt6Gui.dll
hwindow1/data/Core/Qt6Network.dll
hwindow1/data/Core/Qt6Pdf.dll
hwindow1/data/Core/Qt6Svg.dll
hwindow1/data/Core/Qt6Widgets.dll
hwindow1/data/Core/d3dcompiler_47.dll
hwindow1/data/Core/data.py
hwindow1/data/Core/data.pyi
hwindow1/data/Core/libgcc_s_seh-1.dll
hwindow1/data/Core/libstdc++-6.dll
hwindow1/data/Core/libwinpthread-1.dll
hwindow1/data/Core/opengl32sw.dll
hwindow1/data/Core/python311.dll
hwindow1/data/Core/vc_redist.x64.exe
hwindow1/data/Core/__pycache__/data.cpython-311.pyc
hwindow1/data/Core/generic/qtuiotouchplugin.dll
hwindow1/data/Core/iconengines/qsvgicon.dll
hwindow1/data/Core/imageformats/qgif.dll
hwindow1/data/Core/imageformats/qicns.dll
hwindow1/data/Core/imageformats/qico.dll
hwindow1/data/Core/imageformats/qjpeg.dll
hwindow1/data/Core/imageformats/qpdf.dll
hwindow1/data/Core/imageformats/qsvg.dll
hwindow1/data/Core/imageformats/qtga.dll
hwindow1/data/Core/imageformats/qtiff.dll
hwindow1/data/Core/imageformats/qwbmp.dll
hwindow1/data/Core/imageformats/qwebp.dll
hwindow1/data/Core/networkinformation/qnetworklistmanager.dll
hwindow1/data/Core/platforms/qdirect2d.dll
hwindow1/data/Core/platforms/qminimal.dll
hwindow1/data/Core/platforms/qoffscreen.dll
hwindow1/data/Core/platforms/qwindows.dll
hwindow1/data/Core/plugins/assetimporters/assimp.dll
hwindow1/data/Core/plugins/assetimporters/assimpd.dll
hwindow1/data/Core/plugins/designer/qaxwidget.dll
hwindow1/data/Core/plugins/designer/qaxwidgetd.dll
hwindow1/data/Core/plugins/designer/qquickwidget.dll
hwindow1/data/Core/plugins/designer/qquickwidgetd.dll
hwindow1/data/Core/plugins/designer/qwebengineview.dll
hwindow1/data/Core/plugins/designer/qwebengineview.pdb
hwindow1/data/Core/plugins/designer/qwebengineviewd.dll
hwindow1/data/Core/plugins/designer/qwebengineviewd.pdb
hwindow1/data/Core/plugins/generic/qinsighttracker.dll
hwindow-1.1.3.dist-info/METADATA
hwindow-1.1.3.dist-info/WHEEL
hwindow-1.1.3.dist-info/top_level.txt
hwindow-1.1.3.dist-info/RECORD
