Metadata-Version: 2.4
Name: hwindow
Version: 1.1.3
Summary: hwindow1
Author: huang yi yi
Author-email: 363766687@qq.com
Requires-Python: >=3.6
License-File: LICENSE.txt
Requires-Dist: PyQt6
Dynamic: author
Dynamic: author-email
Dynamic: description
Dynamic: license-file
Dynamic: requires-dist
Dynamic: requires-python
Dynamic: summary
